micropolarray/__init__.py
micropolarray/cameras.py
micropolarray/image.py
micropolarray/micropol_image.py
micropolarray/polarization_functions.py
micropolarray/utils.py
micropolarray/processing/__init__.py
micropolarray/processing/chen_wan_liang_calibration.py
micropolarray/processing/congrid.py
micropolarray/processing/convert.py
micropolarray/processing/demodulation.py
micropolarray/processing/demodulation_errors.py
micropolarray/processing/demosaic.py
micropolarray/processing/image_cleaning.py
micropolarray/processing/linear_roi.py
micropolarray/processing/nrgf.py
micropolarray/processing/rebin.py
micropolarray/processing/shift.py
micropolarray-1.2.14.dist-info/LICENSE
micropolarray-1.2.14.dist-info/METADATA
micropolarray-1.2.14.dist-info/WHEEL
micropolarray-1.2.14.dist-info/top_level.txt
micropolarray-1.2.14.dist-info/RECORD
