Metadata-Version: 2.1
Name: micropolarray
Version: 1.2.14
Summary: micropolarizer array data utilities
Home-page: https://github.com/Hevil33/micropolarray_master
Author: Hervé Haudemand
Author-email: Herve Haudemand <herve.haudemand@inaf.it>
License: BSD 3-Clause License
Project-URL: Homepage, https://github.com/Hevil33/micropolarray_master
Project-URL: Source code, https://github.com/Hevil33/micropolarray_master
Project-URL: Documentation, https://micropolarray.readthedocs.io/en/latest/
Keywords: micropolarizer,polarcam,polarization,astronomy
Classifier: License :: OSI Approved :: BSD License
Classifier: Programming Language :: Python
Classifier: Programming Language :: Python :: 3
Requires-Python: >=3.8
License-File: LICENSE
Requires-Dist: numpy >=1.26.4
Requires-Dist: pandas
Requires-Dist: numba
Requires-Dist: dataclasses
Requires-Dist: astropy
Requires-Dist: matplotlib
Requires-Dist: scipy
Requires-Dist: scikit-image
Requires-Dist: wheel
Requires-Dist: tqdm
Requires-Dist: pytest
Requires-Dist: sphinx-rtd-theme
Requires-Dist: opencv-python-headless
Provides-Extra: dev
Requires-Dist: black ; extra == 'dev'
Requires-Dist: bumpver ; extra == 'dev'
Requires-Dist: isort ; extra == 'dev'
Requires-Dist: pip-tools ; extra == 'dev'
